CHANGES.txt
COPYRIGHTS.txt
INSTALL.txt
LICENSE.txt
MANIFEST.in
README.txt
setup.cfg
setup.py
./scikits/__init__.py
scikits/__init__.py
scikits.statsmodels.egg-info/PKG-INFO
scikits.statsmodels.egg-info/SOURCES.txt
scikits.statsmodels.egg-info/dependency_links.txt
scikits.statsmodels.egg-info/namespace_packages.txt
scikits.statsmodels.egg-info/not-zip-safe
scikits.statsmodels.egg-info/top_level.txt
scikits/statsmodels/LICENSE.txt
scikits/statsmodels/TODO.txt
scikits/statsmodels/__init__.py
scikits/statsmodels/api.py
scikits/statsmodels/info.py
scikits/statsmodels/version.py
scikits/statsmodels/base/__init__.py
scikits/statsmodels/base/model.py
scikits/statsmodels/compatnp/__init__.py
scikits/statsmodels/compatnp/py3k.py
scikits/statsmodels/datasets/COPYING
scikits/statsmodels/datasets/README.txt
scikits/statsmodels/datasets/__init__.py
scikits/statsmodels/datasets/datautils.py
scikits/statsmodels/datasets/template_data.py
scikits/statsmodels/datasets/anes96/__init__.py
scikits/statsmodels/datasets/anes96/anes96.csv
scikits/statsmodels/datasets/anes96/data.py
scikits/statsmodels/datasets/anes96/src/anes96.csv
scikits/statsmodels/datasets/ccard/R_wls.s
scikits/statsmodels/datasets/ccard/__init__.py
scikits/statsmodels/datasets/ccard/ccard.csv
scikits/statsmodels/datasets/ccard/data.py
scikits/statsmodels/datasets/ccard/src/ccard.csv
scikits/statsmodels/datasets/ccard/src/names.txt
scikits/statsmodels/datasets/committee/R_committee.s
scikits/statsmodels/datasets/committee/__init__.py
scikits/statsmodels/datasets/committee/committee.csv
scikits/statsmodels/datasets/committee/data.py
scikits/statsmodels/datasets/committee/src/committee.dat
scikits/statsmodels/datasets/copper/__init__.py
scikits/statsmodels/datasets/copper/copper.csv
scikits/statsmodels/datasets/copper/data.py
scikits/statsmodels/datasets/copper/src/copper.dat
scikits/statsmodels/datasets/cpunish/R_cpunish.s
scikits/statsmodels/datasets/cpunish/__init__.py
scikits/statsmodels/datasets/cpunish/cpunish.csv
scikits/statsmodels/datasets/cpunish/data.py
scikits/statsmodels/datasets/cpunish/src/cpunish.dat
scikits/statsmodels/datasets/grunfeld/__init__.py
scikits/statsmodels/datasets/grunfeld/data.py
scikits/statsmodels/datasets/grunfeld/grunfeld.csv
